Adafruit_BNO055-1.0.2.dist-info/metadata.json
Adafruit_BNO055-1.0.2.dist-info/METADATA
Adafruit_BNO055-1.0.2.dist-info/RECORD
Adafruit_BNO055-1.0.2.dist-info/WHEEL
Adafruit_BNO055-1.0.2.dist-info/DESCRIPTION.rst
Adafruit_BNO055-1.0.2.dist-info/dependency_links.txt
Adafruit_BNO055-1.0.2.dist-info/top_level.txt
Adafruit_BNO055/BNO055.py
Adafruit_BNO055/__init__.py
